LICENSE.txt
MANIFEST.in
README.md
setup.cfg
setup.py
imagetyperzapi2/__init__.py
imagetyperzapi2/imagetyperzapi.py
imagetyperzapi2.egg-info/PKG-INFO
imagetyperzapi2.egg-info/SOURCES.txt
imagetyperzapi2.egg-info/dependency_links.txt
imagetyperzapi2.egg-info/requires.txt
imagetyperzapi2.egg-info/top_level.txt