Metadata-Version: 1.2
Name: imagetyperzapi2
Version: 0.2
Summary: ImagetyperzAPI Python2 - is a super easy to use bypass captcha API wrapper for imagetyperz.com captcha service
Home-page: https://github.com/imagetyperz-api/imagetyperz-api-python2
Author: Imagetyperz Dev
Author-email: imagetyperz@gmail.com
License: MIT
Download-URL: https://github.com/imagetyperz-api/imagetyperz-api-python2/archive/0.1.tar.gz
Keywords: captcha,bypasscaptcha,decaptcher,decaptcha,2captcha,deathbycaptcha,anticaptcha
Platform: UNKNOWN
Requires-Python: ==2.7.*
